reflex_cli/__init__.py
reflex_cli/child_template_generator.py
reflex_cli/cli.py
reflex_cli/cli_environment.py
reflex_cli/config_parser.py
reflex_cli/config_version_updater.py
reflex_cli/create_template_utils.py
reflex_cli/package_generator.py
reflex_cli/reflex_cli.py
reflex_cli/reflex_github.py
reflex_cli/reflex_initializer.py
reflex_cli/region_template_generator.py
reflex_cli/repo_foundation_skeleton.py
reflex_cli/rule.py
reflex_cli/rule_discoverer.py
reflex_cli/template_generator.py
reflex_cli/terraform_skeleton.py
reflex_cli/user_input.py
reflex_cli/commands/__init__.py
reflex_cli/commands/command_build.py
reflex_cli/commands/command_create.py
reflex_cli/commands/command_init.py
reflex_cli/commands/command_package.py
reflex_cli/commands/command_region.py
reflex_cli/commands/command_show.py
reflex_cli/commands/command_upgrade.py
reflex_cli/templates/aws-rule-child.tf
reflex_cli/templates/aws-rule-region.tf
reflex_cli/templates/aws-rule.tf
reflex_cli/templates/backend.tf
reflex_cli/templates/central-sns-topic.tf
reflex_cli/templates/provider.tf
reflex_cli/templates/reflex-kms-key.tf
reflex_cli/templates/reflex.yaml.jinja2
reflex_cli/templates/rule_templates/.gitignore
reflex_cli/templates/rule_templates/.pylintrc
reflex_cli/templates/rule_templates/LICENSE
reflex_cli/templates/rule_templates/README.md
reflex_cli/templates/rule_templates/.github/.releaserc.json.jinja2
reflex_cli/templates/rule_templates/.github/renovate.json.jinja2
reflex_cli/templates/rule_templates/.github/workflows/release.yaml.jinja2
reflex_cli/templates/rule_templates/.github/workflows/test.yaml.jinja2
reflex_cli/templates/rule_templates/source/requirements.txt
reflex_cli/templates/rule_templates/source/rule.py.jinja2
reflex_cli/templates/rule_templates/terraform/assume_role/assume_role.tf.jinja2
reflex_cli/templates/rule_templates/terraform/assume_role/variables.tf
reflex_cli/templates/rule_templates/terraform/cwe/main.tf
reflex_cli/templates/rule_templates/terraform/cwe/output.tf
reflex_cli-1.3.3.dist-info/LICENSE
reflex_cli-1.3.3.dist-info/METADATA
reflex_cli-1.3.3.dist-info/WHEEL
reflex_cli-1.3.3.dist-info/entry_points.txt
reflex_cli-1.3.3.dist-info/top_level.txt
reflex_cli-1.3.3.dist-info/RECORD
