Metadata-Version: 2.1
Name: reflex-cli
Version: 1.3.3
Summary: UNKNOWN
Home-page: UNKNOWN
Author: UNKNOWN
Author-email: UNKNOWN
License: UNKNOWN
Platform: UNKNOWN
Requires-Dist: click
Requires-Dist: jinja2
Requires-Dist: pyyaml
Requires-Dist: requests
Requires-Dist: pyhcl
Requires-Dist: pyinquirer
Requires-Dist: pygithub
